markie/__init__.py
markie/doc.py
markie/utils.py
markie/rules/__init__.py
markie/rules/parsing_rules.py
markie/rules/render_rules.py
markie-0.0.1a3.dist-info/LICENSE
markie-0.0.1a3.dist-info/METADATA
markie-0.0.1a3.dist-info/WHEEL
markie-0.0.1a3.dist-info/top_level.txt
markie-0.0.1a3.dist-info/RECORD
