Metadata-Version: 2.1
Name: markie
Version: 0.0.1a3
Summary: Small package for easily processing markdown files
License: MIT License
Project-URL: repository, https://github.com/James-Ansley/markie
Classifier: Development Status :: 1 - Planning
Classifier: Topic :: Utilities
Classifier: Programming Language :: Python :: 3
Classifier: License :: OSI Approved :: MIT License
Requires-Python: >=3.11
License-File: LICENSE
Requires-Dist: PyYAML ~=6.0.1
Requires-Dist: markdown-it-py ~=2.2.0
Requires-Dist: mdformat ~=0.7.17
Requires-Dist: mdformat-footnote ~=0.1.1
Requires-Dist: mdformat-frontmatter ~=2.0.1
Requires-Dist: mdformat-tables ~=0.4.1
Requires-Dist: mdit-py-plugins ~=0.3.5
Requires-Dist: mdurl ~=0.1.2
